dimitar_multiply/__init__.py
dimitar_multiply/multiplication.py
dimitar_multiply-0.1.1.dist-info/METADATA
dimitar_multiply-0.1.1.dist-info/WHEEL
dimitar_multiply-0.1.1.dist-info/top_level.txt
dimitar_multiply-0.1.1.dist-info/RECORD
